[{"metadata": {"name": "knb-478591", "generator": "knb", "version": "1.5.0", "date": "2023-05-22 09:37:57", "server-node": "l26-node03", "client-node": "l26-node02", "socket-buffer-size": "2M"}, "data": {"cpu": "Intel(R) Xeon(R) CPU X5647 @ 2.93GHz", "kernel": "5.15.0-72-generic", "k8s-version": "v1.22.17+k3s1", "mtu": "1230", "idle": {"bandwidth": 0, "client": {"cpu": {"total": 1.65, "user": 0.86, "nice": 0.0, "system": 0.46, "iowait": 0.33, "steal": 0.0}, "ram": 696}, "server": {"cpu": {"total": 2.04, "user": 1.23, "nice": 0.0, "system": 0.67, "iowait": 0.14, "steal": 0.0}, "ram": 779}}, "pod2pod": {"tcp": {"bandwidth": 22.7, "client": {"cpu": {"total": 2.3, "user": 0.68, "nice": 0.0, "system": 1.43, "iowait": 0.19, "steal": 0.0}, "ram": 731}, "server": {"cpu": {"total": 2.8, "user": 1.21, "nice": 0.0, "system": 1.51, "iowait": 0.08, "steal": 0.0}, "ram": 793}}, "udp": {"bandwidth": 26.6, "client": {"cpu": {"total": 13.6, "user": 1.2, "nice": 0.0, "system": 12.2, "iowait": 0.2, "steal": 0.0}, "ram": 729}, "server": {"cpu": {"total": 2.67, "user": 1.16, "nice": 0.0, "system": 1.44, "iowait": 0.07, "steal": 0.0}, "ram": 789}}}, "pod2svc": {"tcp": {"bandwidth": 21.6, "client": {"cpu": {"total": 1.89, "user": 0.56, "nice": 0.0, "system": 1.16, "iowait": 0.17, "steal": 0.0}, "ram": 697}, "server": {"cpu": {"total": 2.72, "user": 1.2, "nice": 0.0, "system": 1.44, "iowait": 0.08, "steal": 0.0}, "ram": 803}}, "udp": {"bandwidth": 26.6, "client": {"cpu": {"total": 13.07, "user": 0.96, "nice": 0.0, "system": 11.96, "iowait": 0.15, "steal": 0.0}, "ram": 703}, "server": {"cpu": {"total": 2.62, "user": 1.2, "nice": 0.0, "system": 1.34, "iowait": 0.08, "steal": 0.0}, "ram": 802}}}}}, {"metadata": {"name": "knb-502802", "generator": "knb", "version": "1.5.0", "date": "2023-05-22 10:09:14", "server-node": "l26-node03", "client-node": "l26-node02", "socket-buffer-size": "2M"}, "data": {"cpu": "Intel(R) Xeon(R) CPU X5647 @ 2.93GHz", "kernel": "5.15.0-72-generic", "k8s-version": "v1.22.17+k3s1", "mtu": "1230", "idle": {"bandwidth": 0, "client": {"cpu": {"total": 1.47, "user": 0.68, "nice": 0.0, "system": 0.44, "iowait": 0.35, "steal": 0.0}, "ram": 698}, "server": {"cpu": {"total": 1.82, "user": 1.11, "nice": 0.0, "system": 0.61, "iowait": 0.1, "steal": 0.0}, "ram": 792}}, "pod2pod": {"tcp": {"bandwidth": 23.0, "client": {"cpu": {"total": 2.13, "user": 0.72, "nice": 0.0, "system": 1.19, "iowait": 0.22, "steal": 0.0}, "ram": 727}, "server": {"cpu": {"total": 2.8, "user": 1.16, "nice": 0.0, "system": 1.57, "iowait": 0.07, "steal": 0.0}, "ram": 804}}, "udp": {"bandwidth": 26.6, "client": {"cpu": {"total": 13.6, "user": 1.23, "nice": 0.0, "system": 12.07, "iowait": 0.3, "steal": 0.0}, "ram": 714}, "server": {"cpu": {"total": 2.68, "user": 1.13, "nice": 0.0, "system": 1.47, "iowait": 0.08, "steal": 0.0}, "ram": 806}}}, "pod2svc": {"tcp": {"bandwidth": 22.3, "client": {"cpu": {"total": 1.99, "user": 0.61, "nice": 0.0, "system": 1.28, "iowait": 0.1, "steal": 0.0}, "ram": 701}, "server": {"cpu": {"total": 2.77, "user": 1.12, "nice": 0.0, "system": 1.58, "iowait": 0.07, "steal": 0.0}, "ram": 799}}, "udp": {"bandwidth": 26.5, "client": {"cpu": {"total": 13.26, "user": 1.0, "nice": 0.0, "system": 12.17, "iowait": 0.09, "steal": 0.0}, "ram": 700}, "server": {"cpu": {"total": 2.8, "user": 1.26, "nice": 0.0, "system": 1.46, "iowait": 0.08, "steal": 0.0}, "ram": 801}}}}}, {"metadata": {"name": "knb-472441", "generator": "knb", "version": "1.5.0", "date": "2023-05-22 09:30:08", "server-node": "l26-node03", "client-node": "l26-node02", "socket-buffer-size": "2M"}, "data": {"cpu": "Intel(R) Xeon(R) CPU X5647 @ 2.93GHz", "kernel": "5.15.0-72-generic", "k8s-version": "v1.22.17+k3s1", "mtu": "1230", "idle": {"bandwidth": 0, "client": {"cpu": {"total": 1.26, "user": 0.61, "nice": 0.0, "system": 0.38, "iowait": 0.27, "steal": 0.0}, "ram": 692}, "server": {"cpu": {"total": 1.95, "user": 1.19, "nice": 0.0, "system": 0.63, "iowait": 0.13, "steal": 0.0}, "ram": 782}}, "pod2pod": {"tcp": {"bandwidth": 22.1, "client": {"cpu": {"total": 1.93, "user": 0.53, "nice": 0.0, "system": 1.25, "iowait": 0.15, "steal": 0.0}, "ram": 697}, "server": {"cpu": {"total": 2.86, "user": 1.21, "nice": 0.0, "system": 1.58, "iowait": 0.07, "steal": 0.0}, "ram": 790}}, "udp": {"bandwidth": 26.6, "client": {"cpu": {"total": 13.52, "user": 1.16, "nice": 0.0, "system": 12.14, "iowait": 0.22, "steal": 0.0}, "ram": 703}, "server": {"cpu": {"total": 3.0, "user": 1.36, "nice": 0.0, "system": 1.57, "iowait": 0.07, "steal": 0.0}, "ram": 792}}}, "pod2svc": {"tcp": {"bandwidth": 21.9, "client": {"cpu": {"total": 1.84, "user": 0.58, "nice": 0.0, "system": 1.17, "iowait": 0.09, "steal": 0.0}, "ram": 698}, "server": {"cpu": {"total": 2.76, "user": 1.18, "nice": 0.0, "system": 1.49, "iowait": 0.09, "steal": 0.0}, "ram": 791}}, "udp": {"bandwidth": 26.6, "client": {"cpu": {"total": 13.06, "user": 0.94, "nice": 0.0, "system": 11.99, "iowait": 0.13, "steal": 0.0}, "ram": 696}, "server": {"cpu": {"total": 2.81, "user": 1.2, "nice": 0.0, "system": 1.54, "iowait": 0.07, "steal": 0.0}, "ram": 793}}}}}, {"metadata": {"name": "knb-496748", "generator": "knb", "version": "1.5.0", "date": "2023-05-22 10:01:25", "server-node": "l26-node03", "client-node": "l26-node02", "socket-buffer-size": "2M"}, "data": {"cpu": "Intel(R) Xeon(R) CPU X5647 @ 2.93GHz", "kernel": "5.15.0-72-generic", "k8s-version": "v1.22.17+k3s1", "mtu": "1230", "idle": {"bandwidth": 0, "client": {"cpu": {"total": 1.63, "user": 0.72, "nice": 0.0, "system": 0.42, "iowait": 0.49, "steal": 0.0}, "ram": 695}, "server": {"cpu": {"total": 2.0, "user": 1.24, "nice": 0.0, "system": 0.6, "iowait": 0.16, "steal": 0.0}, "ram": 791}}, "pod2pod": {"tcp": {"bandwidth": 23.1, "client": {"cpu": {"total": 1.98, "user": 0.59, "nice": 0.0, "system": 1.21, "iowait": 0.18, "steal": 0.0}, "ram": 703}, "server": {"cpu": {"total": 2.91, "user": 1.22, "nice": 0.0, "system": 1.61, "iowait": 0.08, "steal": 0.0}, "ram": 807}}, "udp": {"bandwidth": 26.6, "client": {"cpu": {"total": 13.44, "user": 1.14, "nice": 0.0, "system": 12.17, "iowait": 0.13, "steal": 0.0}, "ram": 701}, "server": {"cpu": {"total": 2.83, "user": 1.32, "nice": 0.0, "system": 1.44, "iowait": 0.07, "steal": 0.0}, "ram": 804}}}, "pod2svc": {"tcp": {"bandwidth": 23.1, "client": {"cpu": {"total": 1.97, "user": 0.59, "nice": 0.0, "system": 1.28, "iowait": 0.1, "steal": 0.0}, "ram": 700}, "server": {"cpu": {"total": 2.81, "user": 1.11, "nice": 0.0, "system": 1.62, "iowait": 0.08, "steal": 0.0}, "ram": 797}}, "udp": {"bandwidth": 26.6, "client": {"cpu": {"total": 12.95, "user": 0.9, "nice": 0.0, "system": 11.88, "iowait": 0.17, "steal": 0.0}, "ram": 700}, "server": {"cpu": {"total": 2.84, "user": 1.22, "nice": 0.0, "system": 1.55, "iowait": 0.07, "steal": 0.0}, "ram": 799}}}}}, {"metadata": {"name": "knb-484676", "generator": "knb", "version": "1.5.0", "date": "2023-05-22 09:45:48", "server-node": "l26-node03", "client-node": "l26-node02", "socket-buffer-size": "2M"}, "data": {"cpu": "Intel(R) Xeon(R) CPU X5647 @ 2.93GHz", "kernel": "5.15.0-72-generic", "k8s-version": "v1.22.17+k3s1", "mtu": "1230", "idle": {"bandwidth": 0, "client": {"cpu": {"total": 1.64, "user": 0.75, "nice": 0.0, "system": 0.46, "iowait": 0.43, "steal": 0.0}, "ram": 699}, "server": {"cpu": {"total": 2.0, "user": 1.24, "nice": 0.0, "system": 0.62, "iowait": 0.14, "steal": 0.0}, "ram": 791}}, "pod2pod": {"tcp": {"bandwidth": 22.7, "client": {"cpu": {"total": 2.4, "user": 0.83, "nice": 0.0, "system": 1.32, "iowait": 0.25, "steal": 0.0}, "ram": 720}, "server": {"cpu": {"total": 2.82, "user": 1.24, "nice": 0.0, "system": 1.5, "iowait": 0.08, "steal": 0.0}, "ram": 802}}, "udp": {"bandwidth": 26.6, "client": {"cpu": {"total": 13.55, "user": 1.2, "nice": 0.0, "system": 12.11, "iowait": 0.24, "steal": 0.0}, "ram": 720}, "server": {"cpu": {"total": 2.68, "user": 1.16, "nice": 0.0, "system": 1.45, "iowait": 0.07, "steal": 0.0}, "ram": 802}}}, "pod2svc": {"tcp": {"bandwidth": 22.5, "client": {"cpu": {"total": 1.94, "user": 0.54, "nice": 0.0, "system": 1.24, "iowait": 0.16, "steal": 0.0}, "ram": 701}, "server": {"cpu": {"total": 2.76, "user": 1.15, "nice": 0.0, "system": 1.51, "iowait": 0.1, "steal": 0.0}, "ram": 797}}, "udp": {"bandwidth": 26.6, "client": {"cpu": {"total": 13.08, "user": 1.05, "nice": 0.0, "system": 11.93, "iowait": 0.1, "steal": 0.0}, "ram": 698}, "server": {"cpu": {"total": 2.74, "user": 1.2, "nice": 0.0, "system": 1.47, "iowait": 0.07, "steal": 0.0}, "ram": 795}}}}}, {"metadata": {"name": "knb-508805", "generator": "knb", "version": "1.5.0", "date": "2023-05-22 10:17:01", "server-node": "l26-node03", "client-node": "l26-node02", "socket-buffer-size": "2M"}, "data": {"cpu": "Intel(R) Xeon(R) CPU X5647 @ 2.93GHz", "kernel": "5.15.0-72-generic", "k8s-version": "v1.22.17+k3s1", "mtu": "1230", "idle": {"bandwidth": 0, "client": {"cpu": {"total": 1.63, "user": 0.87, "nice": 0.0, "system": 0.42, "iowait": 0.34, "steal": 0.0}, "ram": 700}, "server": {"cpu": {"total": 1.91, "user": 1.14, "nice": 0.0, "system": 0.62, "iowait": 0.15, "steal": 0.0}, "ram": 793}}, "pod2pod": {"tcp": {"bandwidth": 23.2, "client": {"cpu": {"total": 2.06, "user": 0.63, "nice": 0.0, "system": 1.29, "iowait": 0.14, "steal": 0.0}, "ram": 725}, "server": {"cpu": {"total": 2.84, "user": 1.18, "nice": 0.0, "system": 1.59, "iowait": 0.07, "steal": 0.0}, "ram": 807}}, "udp": {"bandwidth": 26.6, "client": {"cpu": {"total": 13.51, "user": 1.21, "nice": 0.0, "system": 12.0, "iowait": 0.3, "steal": 0.0}, "ram": 716}, "server": {"cpu": {"total": 2.91, "user": 1.33, "nice": 0.0, "system": 1.47, "iowait": 0.11, "steal": 0.0}, "ram": 801}}}, "pod2svc": {"tcp": {"bandwidth": 22.4, "client": {"cpu": {"total": 1.85, "user": 0.55, "nice": 0.0, "system": 1.22, "iowait": 0.08, "steal": 0.0}, "ram": 700}, "server": {"cpu": {"total": 2.89, "user": 1.18, "nice": 0.0, "system": 1.64, "iowait": 0.07, "steal": 0.0}, "ram": 801}}, "udp": {"bandwidth": 26.6, "client": {"cpu": {"total": 13.21, "user": 0.98, "nice": 0.0, "system": 12.11, "iowait": 0.12, "steal": 0.0}, "ram": 701}, "server": {"cpu": {"total": 2.77, "user": 1.26, "nice": 0.0, "system": 1.44, "iowait": 0.07, "steal": 0.0}, "ram": 800}}}}}, {"metadata": {"name": "knb-490704", "generator": "knb", "version": "1.5.0", "date": "2023-05-22 09:53:36", "server-node": "l26-node03", "client-node": "l26-node02", "socket-buffer-size": "2M"}, "data": {"cpu": "Intel(R) Xeon(R) CPU X5647 @ 2.93GHz", "kernel": "5.15.0-72-generic", "k8s-version": "v1.22.17+k3s1", "mtu": "1230", "idle": {"bandwidth": 0, "client": {"cpu": {"total": 1.35, "user": 0.67, "nice": 0.0, "system": 0.39, "iowait": 0.29, "steal": 0.0}, "ram": 693}, "server": {"cpu": {"total": 1.94, "user": 1.17, "nice": 0.0, "system": 0.63, "iowait": 0.14, "steal": 0.0}, "ram": 797}}, "pod2pod": {"tcp": {"bandwidth": 22.9, "client": {"cpu": {"total": 2.18, "user": 0.62, "nice": 0.0, "system": 1.34, "iowait": 0.22, "steal": 0.0}, "ram": 729}, "server": {"cpu": {"total": 2.86, "user": 1.14, "nice": 0.0, "system": 1.64, "iowait": 0.08, "steal": 0.0}, "ram": 800}}, "udp": {"bandwidth": 26.6, "client": {"cpu": {"total": 13.46, "user": 1.14, "nice": 0.0, "system": 12.11, "iowait": 0.21, "steal": 0.0}, "ram": 722}, "server": {"cpu": {"total": 2.7, "user": 1.16, "nice": 0.0, "system": 1.46, "iowait": 0.08, "steal": 0.0}, "ram": 801}}}, "pod2svc": {"tcp": {"bandwidth": 22.8, "client": {"cpu": {"total": 2.16, "user": 0.68, "nice": 0.0, "system": 1.34, "iowait": 0.14, "steal": 0.0}, "ram": 727}, "server": {"cpu": {"total": 2.93, "user": 1.26, "nice": 0.0, "system": 1.6, "iowait": 0.07, "steal": 0.0}, "ram": 800}}, "udp": {"bandwidth": 26.6, "client": {"cpu": {"total": 13.25, "user": 1.09, "nice": 0.0, "system": 11.96, "iowait": 0.2, "steal": 0.0}, "ram": 712}, "server": {"cpu": {"total": 2.8, "user": 1.17, "nice": 0.0, "system": 1.53, "iowait": 0.1, "steal": 0.0}, "ram": 803}}}}}, {"metadata": {"name": "knb-514989", "generator": "knb", "version": "1.5.0", "date": "2023-05-22 10:24:51", "server-node": "l26-node03", "client-node": "l26-node02", "socket-buffer-size": "2M"}, "data": {"cpu": "Intel(R) Xeon(R) CPU X5647 @ 2.93GHz", "kernel": "5.15.0-72-generic", "k8s-version": "v1.22.17+k3s1", "mtu": "1230", "idle": {"bandwidth": 0, "client": {"cpu": {"total": 1.36, "user": 0.66, "nice": 0.0, "system": 0.44, "iowait": 0.26, "steal": 0.0}, "ram": 695}, "server": {"cpu": {"total": 2.08, "user": 1.26, "nice": 0.0, "system": 0.67, "iowait": 0.15, "steal": 0.0}, "ram": 793}}, "pod2pod": {"tcp": {"bandwidth": 22.7, "client": {"cpu": {"total": 2.03, "user": 0.61, "nice": 0.0, "system": 1.29, "iowait": 0.13, "steal": 0.0}, "ram": 727}, "server": {"cpu": {"total": 2.85, "user": 1.16, "nice": 0.0, "system": 1.61, "iowait": 0.08, "steal": 0.0}, "ram": 806}}, "udp": {"bandwidth": 26.6, "client": {"cpu": {"total": 13.54, "user": 1.13, "nice": 0.0, "system": 12.0, "iowait": 0.41, "steal": 0.0}, "ram": 723}, "server": {"cpu": {"total": 3.06, "user": 1.43, "nice": 0.0, "system": 1.55, "iowait": 0.08, "steal": 0.0}, "ram": 804}}}, "pod2svc": {"tcp": {"bandwidth": 22.9, "client": {"cpu": {"total": 1.97, "user": 0.53, "nice": 0.0, "system": 1.27, "iowait": 0.17, "steal": 0.0}, "ram": 700}, "server": {"cpu": {"total": 2.81, "user": 1.13, "nice": 0.0, "system": 1.61, "iowait": 0.07, "steal": 0.0}, "ram": 808}}, "udp": {"bandwidth": 26.6, "client": {"cpu": {"total": 13.25, "user": 1.01, "nice": 0.0, "system": 12.14, "iowait": 0.1, "steal": 0.0}, "ram": 705}, "server": {"cpu": {"total": 2.74, "user": 1.23, "nice": 0.0, "system": 1.44, "iowait": 0.07, "steal": 0.0}, "ram": 801}}}}}, {"metadata": {"name": "knb-521156", "generator": "knb", "version": "1.5.0", "date": "2023-05-22 10:32:40", "server-node": "l26-node03", "client-node": "l26-node02", "socket-buffer-size": "2M"}, "data": {"cpu": "Intel(R) Xeon(R) CPU X5647 @ 2.93GHz", "kernel": "5.15.0-72-generic", "k8s-version": "v1.22.17+k3s1", "mtu": "1230", "idle": {"bandwidth": 0, "client": {"cpu": {"total": 1.36, "user": 0.63, "nice": 0.0, "system": 0.41, "iowait": 0.32, "steal": 0.0}, "ram": 696}, "server": {"cpu": {"total": 1.93, "user": 1.18, "nice": 0.0, "system": 0.64, "iowait": 0.11, "steal": 0.0}, "ram": 795}}, "pod2pod": {"tcp": {"bandwidth": 21.6, "client": {"cpu": {"total": 2.02, "user": 0.67, "nice": 0.0, "system": 1.19, "iowait": 0.16, "steal": 0.0}, "ram": 731}, "server": {"cpu": {"total": 2.78, "user": 1.18, "nice": 0.0, "system": 1.52, "iowait": 0.08, "steal": 0.0}, "ram": 800}}, "udp": {"bandwidth": 26.6, "client": {"cpu": {"total": 13.49, "user": 1.13, "nice": 0.0, "system": 11.93, "iowait": 0.43, "steal": 0.0}, "ram": 725}, "server": {"cpu": {"total": 2.7, "user": 1.17, "nice": 0.0, "system": 1.45, "iowait": 0.08, "steal": 0.0}, "ram": 801}}}, "pod2svc": {"tcp": {"bandwidth": 21.5, "client": {"cpu": {"total": 1.93, "user": 0.57, "nice": 0.0, "system": 1.18, "iowait": 0.18, "steal": 0.0}, "ram": 705}, "server": {"cpu": {"total": 2.76, "user": 1.15, "nice": 0.0, "system": 1.53, "iowait": 0.08, "steal": 0.0}, "ram": 800}}, "udp": {"bandwidth": 26.6, "client": {"cpu": {"total": 13.27, "user": 1.0, "nice": 0.0, "system": 12.18, "iowait": 0.09, "steal": 0.0}, "ram": 698}, "server": {"cpu": {"total": 2.62, "user": 1.15, "nice": 0.0, "system": 1.39, "iowait": 0.08, "steal": 0.0}, "ram": 798}}}}}, {"metadata": {"name": "knb-527285", "generator": "knb", "version": "1.5.0", "date": "2023-05-22 10:40:38", "server-node": "l26-node03", "client-node": "l26-node02", "socket-buffer-size": "2M"}, "data": {"cpu": "Intel(R) Xeon(R) CPU X5647 @ 2.93GHz", "kernel": "5.15.0-72-generic", "k8s-version": "v1.22.17+k3s1", "mtu": "1230", "idle": {"bandwidth": 0, "client": {"cpu": {"total": 1.6, "user": 0.87, "nice": 0.0, "system": 0.43, "iowait": 0.3, "steal": 0.0}, "ram": 702}, "server": {"cpu": {"total": 1.82, "user": 1.11, "nice": 0.0, "system": 0.6, "iowait": 0.11, "steal": 0.0}, "ram": 790}}, "pod2pod": {"tcp": {"bandwidth": 22.8, "client": {"cpu": {"total": 2.12, "user": 0.61, "nice": 0.0, "system": 1.32, "iowait": 0.19, "steal": 0.0}, "ram": 733}, "server": {"cpu": {"total": 2.89, "user": 1.2, "nice": 0.0, "system": 1.62, "iowait": 0.07, "steal": 0.0}, "ram": 801}}, "udp": {"bandwidth": 26.6, "client": {"cpu": {"total": 13.46, "user": 1.2, "nice": 0.0, "system": 11.97, "iowait": 0.29, "steal": 0.0}, "ram": 723}, "server": {"cpu": {"total": 2.74, "user": 1.24, "nice": 0.0, "system": 1.42, "iowait": 0.08, "steal": 0.0}, "ram": 803}}}, "pod2svc": {"tcp": {"bandwidth": 22.4, "client": {"cpu": {"total": 1.9, "user": 0.55, "nice": 0.0, "system": 1.21, "iowait": 0.14, "steal": 0.0}, "ram": 704}, "server": {"cpu": {"total": 2.71, "user": 1.09, "nice": 0.0, "system": 1.55, "iowait": 0.07, "steal": 0.0}, "ram": 801}}, "udp": {"bandwidth": 26.6, "client": {"cpu": {"total": 13.13, "user": 0.97, "nice": 0.0, "system": 12.03, "iowait": 0.13, "steal": 0.0}, "ram": 702}, "server": {"cpu": {"total": 2.99, "user": 1.32, "nice": 0.0, "system": 1.57, "iowait": 0.1, "steal": 0.0}, "ram": 808}}}}}]